xploiter/_init_.py
xploiter/xploiter.py
xploiter-0.1.1.dist-info/METADATA
xploiter-0.1.1.dist-info/WHEEL
xploiter-0.1.1.dist-info/top_level.txt
xploiter-0.1.1.dist-info/RECORD
