Metadata-Version: 2.4
Name: xploiter
Version: 0.1.1
Summary: A simple Pandas-based employee data cleaning utility
Author: Xploiter
License: MIT
Requires-Python: >=3.8
Requires-Dist: pandas>=1.5
